xls_is_for_corporate/__init__.py
xls_is_for_corporate/converter.py
xls_is_for_corporate/table_utils.py
xls_is_for_corporate/xlsifc.py
xls_is_for_corporate-1.0.1.dist-info/METADATA
xls_is_for_corporate-1.0.1.dist-info/WHEEL
xls_is_for_corporate-1.0.1.dist-info/entry_points.txt
xls_is_for_corporate-1.0.1.dist-info/RECORD
